{
    "display": {
        "icon": {
            "item": "erebus:ore_petrified_wood"
        },
		"title": {
			"translate": "advancement.erebus.exploration.petrified_wood"
		},
		"description": {
			"translate": "advancement.erebus.exploration.petrified_wood.desc"
		},
		"hidden": true
	},
	"parent": "erebus:exploration/root",
	"criteria": {
		"petrified_wood": {
			"trigger": "minecraft:inventory_changed",
			"conditions": {
				"items": [
					{
					"item": "erebus:materials",
					"data": 7
					}
				]
			}
		}
	}
}